{
  "@context": "https://schema.org",
  "generated_at": "2026-06-22T21:42:42.616Z",
  "base_url": "https://example.com",
  "currency": "ILS",
  "count": 1,
  "products": [
    {
      "id": "8df91d76-bbff-445e-86db-ecd2edeaf48f",
      "slug": "lvlh-nvtnt-brash-96ckrf",
      "name": "לולה נותנת בראש",
      "name_translations": {},
      "description": "<p>ציון 8/10</p>",
      "short_description": "בחורה לוהטת מהמובחרות של עמיחי, סוגים:\nצ׳אחלה, מוצא מרוקאי.",
      "sku": null,
      "brand": null,
      "price": 559.9,
      "base_price": 599.9,
      "sale_price": 559.9,
      "currency": "ILS",
      "images": [
        "https://example.com/assets/product-enhanced-1782163811766-awvxr9.webp"
      ],
      "in_stock": true,
      "stock_status": "in_stock",
      "url": "https://example.com/product/lvlh-nvtnt-brash-96ckrf",
      "categories": [],
      "updated_at": "2026-06-22T21:31:48.498Z"
    }
  ]
}